mapbots/__init__.py
mapbots/street_sweeper.py
mapbots/tsp.py
mapbots-0.1.8.dist-info/METADATA
mapbots-0.1.8.dist-info/WHEEL
mapbots-0.1.8.dist-info/top_level.txt
mapbots-0.1.8.dist-info/RECORD
